<?xml version="1.0" encoding="UTF-8"?>
<objects serializationModel="Studio.02.01.00">
	<object class="Event" id="{27146663-d069-44fa-a23f-6d059040a637}">
		<property name="name">
			<value>Zone 1</value>
		</property>
		<property name="outputFormat">
			<value>2</value>
		</property>
		<relationship name="folder">
			<destination>{dc5fc090-4198-4f06-a620-bb20d7df4751}</destination>
		</relationship>
		<relationship name="mixer">
			<destination>{54cb4441-a904-48d3-95ad-93bf5c6d1c59}</destination>
		</relationship>
		<relationship name="masterTrack">
			<destination>{be9cd26f-d0bf-42a6-912b-e847f560ee0a}</destination>
		</relationship>
		<relationship name="mixerInput">
			<destination>{c8554202-cb5d-49e8-88b7-9655c9704093}</destination>
		</relationship>
		<relationship name="automatableProperties">
			<destination>{441f4fe0-49e0-4e31-b45c-cec4d8eb6e27}</destination>
		</relationship>
		<relationship name="markerTracks">
			<destination>{3631da40-127f-46ee-b8ac-c69d15f04d5d}</destination>
			<destination>{f7e3b5f1-bc8a-4695-9cc2-995df7f1b8cf}</destination>
		</relationship>
		<relationship name="groupTracks">
			<destination>{145ea4c0-401e-4130-97df-53a2c9ab0c1c}</destination>
		</relationship>
		<relationship name="timeline">
			<destination>{7503793c-6171-439b-9c34-0b319f415a29}</destination>
		</relationship>
		<relationship name="parameters">
			<destination>{74d33608-d806-43ca-8b9a-fe1939a2c0db}</destination>
		</relationship>
		<relationship name="banks">
			<destination>{312af681-03fa-4f0a-97ac-af4d02c4f20c}</destination>
		</relationship>
	</object>
	<object class="EventMixer" id="{54cb4441-a904-48d3-95ad-93bf5c6d1c59}">
		<relationship name="masterBus">
			<destination>{ac6d670c-e670-4274-9f96-26b4ec796330}</destination>
		</relationship>
	</object>
	<object class="MasterTrack" id="{be9cd26f-d0bf-42a6-912b-e847f560ee0a}">
		<relationship name="modules">
			<destination>{9bd2a402-af5e-47a7-a9df-1d8e84519938}</destination>
		</relationship>
		<relationship name="mixerGroup">
			<destination>{ac6d670c-e670-4274-9f96-26b4ec796330}</destination>
		</relationship>
	</object>
	<object class="MixerInput" id="{c8554202-cb5d-49e8-88b7-9655c9704093}">
		<relationship name="effectChain">
			<destination>{365ce305-6759-42b6-a4be-b1673eb19f04}</destination>
		</relationship>
		<relationship name="panner">
			<destination>{0946a7a8-8d59-4cff-87c4-f763074f6823}</destination>
		</relationship>
		<relationship name="output">
			<destination>{75da32b6-f042-4bbf-b07e-b9af9d2c11b4}</destination>
		</relationship>
	</object>
	<object class="EventAutomatableProperties" id="{441f4fe0-49e0-4e31-b45c-cec4d8eb6e27}" />
	<object class="MarkerTrack" id="{3631da40-127f-46ee-b8ac-c69d15f04d5d}" />
	<object class="MarkerTrack" id="{f7e3b5f1-bc8a-4695-9cc2-995df7f1b8cf}" />
	<object class="GroupTrack" id="{145ea4c0-401e-4130-97df-53a2c9ab0c1c}">
		<relationship name="modules">
			<destination>{d22ee996-7235-458d-8bcf-e6673aff2a8d}</destination>
		</relationship>
		<relationship name="mixerGroup">
			<destination>{3da52648-7844-483d-b523-ead5a19185bb}</destination>
		</relationship>
	</object>
	<object class="Timeline" id="{7503793c-6171-439b-9c34-0b319f415a29}">
		<relationship name="modules">
			<destination>{d22ee996-7235-458d-8bcf-e6673aff2a8d}</destination>
		</relationship>
		<relationship name="markers">
			<destination>{29536c8e-433a-43e0-8f69-59e0838b37df}</destination>
			<destination>{21300131-f40f-440b-95cf-6129b411c70f}</destination>
		</relationship>
	</object>
	<object class="ActionSheet" id="{74d33608-d806-43ca-8b9a-fe1939a2c0db}">
		<relationship name="modules">
			<destination>{9bd2a402-af5e-47a7-a9df-1d8e84519938}</destination>
		</relationship>
	</object>
	<object class="EventMixerMaster" id="{ac6d670c-e670-4274-9f96-26b4ec796330}">
		<relationship name="effectChain">
			<destination>{d5d24fcd-a914-4811-b0ff-8404dc9b9208}</destination>
		</relationship>
		<relationship name="panner">
			<destination>{efb74966-da3c-46d1-8b67-fcdcc4752baa}</destination>
		</relationship>
		<relationship name="mixer">
			<destination>{54cb4441-a904-48d3-95ad-93bf5c6d1c59}</destination>
		</relationship>
	</object>
	<object class="MultiSound" id="{9bd2a402-af5e-47a7-a9df-1d8e84519938}" />
	<object class="MixerBusEffectChain" id="{365ce305-6759-42b6-a4be-b1673eb19f04}">
		<relationship name="effects">
			<destination>{2c9d17b8-1736-4c9b-b70c-4fb6eba6786e}</destination>
		</relationship>
	</object>
	<object class="MixerBusPanner" id="{0946a7a8-8d59-4cff-87c4-f763074f6823}" />
	<object class="SoundScatterer" id="{d22ee996-7235-458d-8bcf-e6673aff2a8d}">
		<property name="triggerProbability">
			<value>49.5</value>
		</property>
		<property name="length">
			<value>30</value>
		</property>
		<property name="polyphony">
			<value>3</value>
		</property>
		<property name="spawnDelayType">
			<value>1</value>
		</property>
		<property name="minimumTimeBetweenSounds">
			<value>1000</value>
		</property>
		<property name="maximumTimeBetweenSounds">
			<value>2500</value>
		</property>
		<property name="spawnQuantizationInterval">
			<value>4</value>
		</property>
		<property name="maximumScatterDistance">
			<value>1</value>
		</property>
		<relationship name="modulators">
			<destination>{c4bc7c74-dccc-41eb-b958-caa1ced45ce7}</destination>
		</relationship>
		<relationship name="sound">
			<destination>{0cf1e2c1-e796-4d63-b230-d2c84de8efa8}</destination>
		</relationship>
	</object>
	<object class="EventMixerGroup" id="{3da52648-7844-483d-b523-ead5a19185bb}">
		<property name="name">
			<value>Audio 4</value>
		</property>
		<relationship name="effectChain">
			<destination>{2b3957b4-4d47-4d45-8d59-4d024d99b987}</destination>
		</relationship>
		<relationship name="panner">
			<destination>{4345cf99-93af-4ce7-820d-648d6472100d}</destination>
		</relationship>
		<relationship name="output">
			<destination>{ac6d670c-e670-4274-9f96-26b4ec796330}</destination>
		</relationship>
	</object>
	<object class="TempoMarker" id="{29536c8e-433a-43e0-8f69-59e0838b37df}">
		<property name="position">
			<value>0</value>
		</property>
		<property name="tempo">
			<value>20</value>
		</property>
		<relationship name="timeline">
			<destination>{7503793c-6171-439b-9c34-0b319f415a29}</destination>
		</relationship>
		<relationship name="markerTrack">
			<destination>{3631da40-127f-46ee-b8ac-c69d15f04d5d}</destination>
		</relationship>
	</object>
	<object class="LoopRegion" id="{21300131-f40f-440b-95cf-6129b411c70f}">
		<property name="position">
			<value>0</value>
		</property>
		<property name="length">
			<value>30</value>
		</property>
		<relationship name="timeline">
			<destination>{7503793c-6171-439b-9c34-0b319f415a29}</destination>
		</relationship>
		<relationship name="markerTrack">
			<destination>{f7e3b5f1-bc8a-4695-9cc2-995df7f1b8cf}</destination>
		</relationship>
	</object>
	<object class="MixerBusEffectChain" id="{d5d24fcd-a914-4811-b0ff-8404dc9b9208}">
		<relationship name="effects">
			<destination>{df90b67d-7300-4919-9a40-e3b9111e7138}</destination>
			<destination>{592e9430-01f6-4d2f-a9ee-6ab2e32a1f16}</destination>
		</relationship>
	</object>
	<object class="MixerBusPanner" id="{efb74966-da3c-46d1-8b67-fcdcc4752baa}" />
	<object class="MixerBusFader" id="{2c9d17b8-1736-4c9b-b70c-4fb6eba6786e}" />
	<object class="LFOModulator" id="{c4bc7c74-dccc-41eb-b958-caa1ced45ce7}">
		<property name="nameOfPropertyBeingModulated">
			<value>pitch</value>
		</property>
		<property name="rate">
			<value>0.25999999</value>
		</property>
		<property name="depth">
			<value>0.5</value>
		</property>
	</object>
	<object class="MultiSound" id="{0cf1e2c1-e796-4d63-b230-d2c84de8efa8}">
		<property name="playlistMode">
			<value>3</value>
		</property>
		<relationship name="sounds">
			<destination>{721000ef-ad24-4c9f-b8a7-e7a9dbd339d3}</destination>
		</relationship>
	</object>
	<object class="MixerBusEffectChain" id="{2b3957b4-4d47-4d45-8d59-4d024d99b987}">
		<relationship name="effects">
			<destination>{5bd22c3d-c2f7-4120-bb93-f78aadb8f76d}</destination>
			<destination>{a7613770-2aa4-487f-934f-a2f81ae4bdff}</destination>
		</relationship>
	</object>
	<object class="MixerBusPanner" id="{4345cf99-93af-4ce7-820d-648d6472100d}" />
	<object class="MixerBusFader" id="{df90b67d-7300-4919-9a40-e3b9111e7138}" />
	<object class="SpatialiserEffect" id="{592e9430-01f6-4d2f-a9ee-6ab2e32a1f16}" />
	<object class="MultiSound" id="{721000ef-ad24-4c9f-b8a7-e7a9dbd339d3}">
		<property name="volume">
			<value>-3.5</value>
		</property>
		<property name="pitch">
			<value>-2.79999995</value>
		</property>
		<relationship name="modulators">
			<destination>{0847fc97-0fd9-466e-b80d-1ac72f907aa1}</destination>
		</relationship>
		<relationship name="sounds">
			<destination>{103889ac-dee8-44cc-be8b-df875ccd6d1d}</destination>
			<destination>{0587a2ab-7e19-4e57-8d55-93473ee62ae0}</destination>
			<destination>{46a70290-4158-49f5-9612-1f2e5817b1c1}</destination>
			<destination>{bc07cb34-d60d-4b96-be14-17a24e9cf00f}</destination>
			<destination>{58b78eaa-e2be-451c-a7ac-449154da7b37}</destination>
			<destination>{7e7e7628-9509-47a6-a3f9-53d2e33a458e}</destination>
			<destination>{9fbb3efc-87fe-429e-8e9d-9d33be42d894}</destination>
			<destination>{f52f7f7b-f8a2-4be4-bd0d-532632cf3376}</destination>
			<destination>{1c2d4759-e4db-4de7-a745-2d227a858d99}</destination>
		</relationship>
		<relationship name="playPercentages">
			<destination>{25f9a73a-8d21-489e-9d65-154aa697b82d}</destination>
			<destination>{daf95180-6543-440f-84c8-6d858706a5c1}</destination>
			<destination>{a95e4bd0-1dc8-42a3-9fee-877dba126ce7}</destination>
		</relationship>
	</object>
	<object class="GainEffect" id="{5bd22c3d-c2f7-4120-bb93-f78aadb8f76d}">
		<property name="gain">
			<value>6</value>
		</property>
	</object>
	<object class="MixerBusFader" id="{a7613770-2aa4-487f-934f-a2f81ae4bdff}" />
	<object class="RandomizerModulator" id="{0847fc97-0fd9-466e-b80d-1ac72f907aa1}">
		<property name="nameOfPropertyBeingModulated">
			<value>startOffset</value>
		</property>
	</object>
	<object class="SingleSound" id="{103889ac-dee8-44cc-be8b-df875ccd6d1d}">
		<relationship name="audioFile">
			<destination>{83171ceb-9c2b-48cb-b82d-84c6f609c031}</destination>
		</relationship>
	</object>
	<object class="SingleSound" id="{0587a2ab-7e19-4e57-8d55-93473ee62ae0}">
		<relationship name="audioFile">
			<destination>{c20ead6e-c32b-4d53-8f1b-5a16fc9d338b}</destination>
		</relationship>
	</object>
	<object class="SingleSound" id="{46a70290-4158-49f5-9612-1f2e5817b1c1}">
		<relationship name="audioFile">
			<destination>{71d1915a-9d19-4c55-a379-e1497e73eb3b}</destination>
		</relationship>
	</object>
	<object class="SingleSound" id="{bc07cb34-d60d-4b96-be14-17a24e9cf00f}">
		<relationship name="audioFile">
			<destination>{b8cdc256-3d68-4db9-8579-c2bc2e0f6f45}</destination>
		</relationship>
	</object>
	<object class="SingleSound" id="{58b78eaa-e2be-451c-a7ac-449154da7b37}">
		<relationship name="audioFile">
			<destination>{056c94b5-ece5-4c2e-a8af-c9c1aee193d5}</destination>
		</relationship>
	</object>
	<object class="SingleSound" id="{7e7e7628-9509-47a6-a3f9-53d2e33a458e}">
		<relationship name="audioFile">
			<destination>{21cf4d26-46ad-4e80-bbed-f36309ef5bea}</destination>
		</relationship>
	</object>
	<object class="SingleSound" id="{9fbb3efc-87fe-429e-8e9d-9d33be42d894}">
		<relationship name="audioFile">
			<destination>{d494e61d-dae5-471a-981b-078137913ec6}</destination>
		</relationship>
	</object>
	<object class="SingleSound" id="{f52f7f7b-f8a2-4be4-bd0d-532632cf3376}">
		<relationship name="audioFile">
			<destination>{edf32771-592d-40c8-ae20-2a209edd38c6}</destination>
		</relationship>
	</object>
	<object class="SingleSound" id="{1c2d4759-e4db-4de7-a745-2d227a858d99}">
		<relationship name="audioFile">
			<destination>{0b733aa0-7d54-48fb-b2dd-5c6c8594e098}</destination>
		</relationship>
	</object>
	<object class="PlayPercentage" id="{25f9a73a-8d21-489e-9d65-154aa697b82d}">
		<property name="percentage">
			<value>0</value>
		</property>
		<relationship name="sound">
			<destination>{46a70290-4158-49f5-9612-1f2e5817b1c1}</destination>
		</relationship>
	</object>
	<object class="PlayPercentage" id="{daf95180-6543-440f-84c8-6d858706a5c1}">
		<property name="percentage">
			<value>0</value>
		</property>
		<relationship name="sound">
			<destination>{f52f7f7b-f8a2-4be4-bd0d-532632cf3376}</destination>
		</relationship>
	</object>
	<object class="PlayPercentage" id="{a95e4bd0-1dc8-42a3-9fee-877dba126ce7}">
		<property name="percentage">
			<value>0</value>
		</property>
		<relationship name="sound">
			<destination>{0587a2ab-7e19-4e57-8d55-93473ee62ae0}</destination>
		</relationship>
	</object>
</objects>
