<?xml version="1.0" encoding="UTF-8"?>
<objects serializationModel="Studio.02.02.00">
	<object class="AudioFile" id="{c88b6cf5-b00a-4c32-adf5-b967c7e1adc5}">
		<property name="assetPath">
			<value>SeagullSquawks04.wav</value>
		</property>
		<property name="frequencyInKHz">
			<value>44.0999985</value>
		</property>
		<property name="channelCount">
			<value>1</value>
		</property>
		<property name="length">
			<value>2.7565079365079366</value>
		</property>
		<relationship name="masterAssetFolder">
			<destination>{16625bce-85a7-4d02-a478-905237a58cc6}</destination>
		</relationship>
	</object>
</objects>
